openvino/__init__.py
openvino/model_zoo/__init__.py
openvino/model_zoo/model_api/__init__.py
openvino/model_zoo/model_api/performance_metrics.py
openvino/model_zoo/model_api/adapters/__init__.py
openvino/model_zoo/model_api/adapters/model_adapter.py
openvino/model_zoo/model_api/adapters/openvino_adapter.py
openvino/model_zoo/model_api/adapters/ovms_adapter.py
openvino/model_zoo/model_api/adapters/utils.py
openvino/model_zoo/model_api/models/__init__.py
openvino/model_zoo/model_api/models/background_matting.py
openvino/model_zoo/model_api/models/bert.py
openvino/model_zoo/model_api/models/centernet.py
openvino/model_zoo/model_api/models/classification.py
openvino/model_zoo/model_api/models/ctpn.py
openvino/model_zoo/model_api/models/deblurring.py
openvino/model_zoo/model_api/models/detection_model.py
openvino/model_zoo/model_api/models/detr.py
openvino/model_zoo/model_api/models/faceboxes.py
openvino/model_zoo/model_api/models/hpe_associative_embedding.py
openvino/model_zoo/model_api/models/image_model.py
openvino/model_zoo/model_api/models/instance_segmentation.py
openvino/model_zoo/model_api/models/model.py
openvino/model_zoo/model_api/models/monodepth.py
openvino/model_zoo/model_api/models/open_pose.py
openvino/model_zoo/model_api/models/retinaface.py
openvino/model_zoo/model_api/models/segmentation.py
openvino/model_zoo/model_api/models/ssd.py
openvino/model_zoo/model_api/models/tokens_bert.py
openvino/model_zoo/model_api/models/types.py
openvino/model_zoo/model_api/models/ultra_lightweight_face_detection.py
openvino/model_zoo/model_api/models/utils.py
openvino/model_zoo/model_api/models/yolo.py
openvino/model_zoo/model_api/pipelines/__init__.py
openvino/model_zoo/model_api/pipelines/async_pipeline.py
visualizers/__init__.py
visualizers/drawing_utils.py
visualizers/instance_segmentation.py
otx_modelapi-0.3.0.dist-info/METADATA
otx_modelapi-0.3.0.dist-info/WHEEL
otx_modelapi-0.3.0.dist-info/top_level.txt
otx_modelapi-0.3.0.dist-info/RECORD
